bionty/__init__.py
bionty/_biorecord.py
bionty/_organism.py
bionty/_shared_docstrings.py
bionty/_source.py
bionty/ids.py
bionty/models.py
bionty/uids.py
bionty/base/__init__.py
bionty/base/_display_sources.py
bionty/base/_ontology.py
bionty/base/_ontology_url.py
bionty/base/_public_ontology.py
bionty/base/_settings.py
bionty/base/sources.yaml
bionty/base/dev/__init__.py
bionty/base/dev/_doc_util.py
bionty/base/dev/_handle_sources.py
bionty/base/dev/_io.py
bionty/base/entities/__init__.py
bionty/base/entities/_bfxpipeline.py
bionty/base/entities/_biosample.py
bionty/base/entities/_cellline.py
bionty/base/entities/_cellmarker.py
bionty/base/entities/_celltype.py
bionty/base/entities/_developmentalstage.py
bionty/base/entities/_disease.py
bionty/base/entities/_drug.py
bionty/base/entities/_ethnicity.py
bionty/base/entities/_experimentalfactor.py
bionty/base/entities/_gene.py
bionty/base/entities/_organism.py
bionty/base/entities/_pathway.py
bionty/base/entities/_phenotype.py
bionty/base/entities/_protein.py
bionty/base/entities/_shared_docstrings.py
bionty/base/entities/_tissue.py
bionty/base/scripts/check_ontologies_reachable.py
bionty/base/scripts/generate_bfxpipelines.py
bionty/base/scripts/update_new_ontologies.py
bionty/base/scripts/bfxpipelines_info/custom_pipelines.json
bionty/core/__init__.py
bionty/core/_add_ontology.py
bionty/core/_settings.py
bionty/core/_source.py
bionty/migrations/0028_artifactcellline_created_at_and_more.py
bionty/migrations/0029_alter_cellline_previous_runs_and_more.py
bionty/migrations/0030_rename_publicsource_source_and_more.py
bionty/migrations/0031_alter_cellmarker_name_and_more.py
bionty/migrations/0032_rename_source_name_source_description_and_more.py
bionty/migrations/0033_alter_artifactcellline_artifact_and_more.py
bionty/migrations/0034_alter_source_unique_together.py
bionty/migrations/0035_alter_protein_gene_symbol.py
bionty/migrations/0036_alter_source_artifacts_and_more.py
bionty-2.1.0.dist-info/licenses/LICENSE
bionty-2.1.0.dist-info/WHEEL
bionty-2.1.0.dist-info/METADATA
bionty-2.1.0.dist-info/RECORD
