Metadata-Version: 2.4
Name: bionty
Version: 2.1.0
Summary: Basic biological entities, coupled to public ontologies [`source <https://github.com/laminlabs/bionty/blob/main/bionty/models.py>`__].
Author-email: Lamin Labs <open-source@lamin.ai>
Requires-Python: >=3.10,<3.14
Classifier: License :: OSI Approved :: Apache Software License
Classifier: Programming Language :: Python :: 3.10
Classifier: Programming Language :: Python :: 3.11
Classifier: Programming Language :: Python :: 3.12
Classifier: Programming Language :: Python :: 3.13
License-File: LICENSE
Requires-Dist: lamindb>=2.0a1
Requires-Dist: lamindb_setup>=0.81.2
Requires-Dist: lamin_utils>=0.16.2
Requires-Dist: requests
Requires-Dist: pyyaml
Requires-Dist: laminci ; extra == "dev"
Requires-Dist: pre-commit ; extra == "dev"
Requires-Dist: pytest>=6.0 ; extra == "dev"
Requires-Dist: pytest-cov ; extra == "dev"
Requires-Dist: nbproject-test ; extra == "dev"
Requires-Dist: pronto ; extra == "dev"
Requires-Dist: pymysql ; extra == "dev"
Requires-Dist: bioregistry ; extra == "dev"
Project-URL: Home, https://github.com/laminlabs/bionty
Provides-Extra: dev
